LICENSE
MANIFEST.in
README.md
remotail.py
requirements.txt
setup.py
remotail.egg-info/PKG-INFO
remotail.egg-info/SOURCES.txt
remotail.egg-info/dependency_links.txt
remotail.egg-info/requires.txt
remotail.egg-info/top_level.txt