Metadata-Version: 1.0
Name: remotail
Version: 0.1.1
Summary: Tail multiple remote files on a terminal window
Home-page: https://github.com/abhinavsingh/remotail
Author: Abhinav Singh
Author-email: mailsforabhinav@gmail.com
License: BSD
Platform: UNKNOWN
Classifier: Development Status :: 4 - Beta
Classifier: Environment :: Console
Classifier: Environment :: Console :: Curses
Classifier: Intended Audience :: Developers
Classifier: Intended Audience :: System Administrators
Classifier: License :: OSI Approved :: BSD License
Classifier: Operating System :: MacOS
Classifier: Operating System :: POSIX
Classifier: Operating System :: Unix
Classifier: Programming Language :: Python :: 2.7
Classifier: Topic :: System :: Monitoring
Classifier: Topic :: Utilities
